augwrap/__init__.py
augwrap/augmentations.py
augwrap/data.py
augwrap/kelvin_table.json
augwrap/transforms.py
augwrap/utils/__init__.py
augwrap/utils/chart.py
augwrap-0.0.1a2.dist-info/LICENSE
augwrap-0.0.1a2.dist-info/METADATA
augwrap-0.0.1a2.dist-info/WHEEL
augwrap-0.0.1a2.dist-info/top_level.txt
augwrap-0.0.1a2.dist-info/RECORD
