Metadata-Version: 2.1
Name: augwrap
Version: 0.0.1a2
Summary: Image augmentation auxiliary tool
Home-page: https://github.com/jinoan/augwrap.git
Author: jinoan
Author-email: jinoan89@gmail.com
License: UNKNOWN
Platform: UNKNOWN
Classifier: Programming Language :: Python :: 3
Classifier: License :: OSI Approved :: MIT License
Requires-Python: >=3.6
License-File: LICENSE
